cosmopharm/__init__.py
cosmopharm/components.py
cosmopharm/actmodels/__init__.py
cosmopharm/actmodels/actmodel.py
cosmopharm/actmodels/cosmo.py
cosmopharm/equilibrium/__init__.py
cosmopharm/equilibrium/lle.py
cosmopharm/equilibrium/sle.py
cosmopharm/utils/__init__.py
cosmopharm/utils/convert.py
cosmopharm/utils/helpers.py
cosmopharm/utils/lle_scanner.py
cosmopharm/utils/spacing.py
cosmopharm-0.1.3.dist-info/licenses/LICENSE
cosmopharm-0.1.3.dist-info/METADATA
cosmopharm-0.1.3.dist-info/WHEEL
cosmopharm-0.1.3.dist-info/top_level.txt
cosmopharm-0.1.3.dist-info/RECORD
