Metadata-Version: 2.4
Name: cosmopharm
Version: 0.1.3
Summary: Predictive modeling for drug-polymer compatibility in pharmaceutical formulations using COSMO-SAC.
Home-page: https://github.com/ivanantolo/cosmopharm
Author: Ivan Antolovic
Author-email: Ivan.Antolovic@tu-berlin.de
Maintainer: Martin Klajmon
Maintainer-email: Martin.Klajmon@vscht.cz
License: MIT
Keywords: Drug-Polymer Compatibility,Amorphous Solid Dispersions,Pharmaceutical Formulation,COSMO-SAC Model,Solubility Prediction,Miscibility Analysis,Phase Behavior Prediction,Pharmaceutical Sciences,Drug Formulation Research,Polymer Science,Predictive Modeling in Pharma,Drug Development Tools,Biopharmaceuticals
Classifier: Development Status :: 3 - Alpha
Classifier: Intended Audience :: Science/Research
Classifier: Intended Audience :: Healthcare Industry
Classifier: Intended Audience :: Developers
Classifier: Intended Audience :: Education
Classifier: License :: OSI Approved :: MIT License
Classifier: Topic :: Scientific/Engineering
Classifier: Topic :: Scientific/Engineering :: Bio-Informatics
Classifier: Topic :: Scientific/Engineering :: Chemistry
Classifier: Programming Language :: Python :: 3
Classifier: Programming Language :: Python :: 3 :: Only
Classifier: Programming Language :: Python :: 3.8
Classifier: Programming Language :: Python :: 3.9
Classifier: Programming Language :: Python :: 3.10
Classifier: Programming Language :: Python :: 3.11
Classifier: Programming Language :: Python :: 3.12
Classifier: Programming Language :: Python :: 3.13
Requires-Python: >=3.8
License-File: LICENSE
Requires-Dist: numpy>=1.15
Requires-Dist: pandas>=1.0
Requires-Dist: scipy>=1.4
Requires-Dist: openpyxl>=3.0
Provides-Extra: examples
Requires-Dist: matplotlib>=3.0; extra == "examples"
Dynamic: description-content-type
Dynamic: license-file
